LICENSE
README.md
pyproject.toml
ixbrl_reporter/__init__.py
ixbrl_reporter/__main__.py
ixbrl_reporter/accounts.py
ixbrl_reporter/accounts_csv.py
ixbrl_reporter/accounts_gnucash.py
ixbrl_reporter/accounts_piecash.py
ixbrl_reporter/basic_element.py
ixbrl_reporter/composite.py
ixbrl_reporter/computation.py
ixbrl_reporter/config.py
ixbrl_reporter/context.py
ixbrl_reporter/data_source.py
ixbrl_reporter/datum.py
ixbrl_reporter/debug_reporter.py
ixbrl_reporter/element.py
ixbrl_reporter/expand.py
ixbrl_reporter/fact.py
ixbrl_reporter/fact_table.py
ixbrl_reporter/flex_sheet.py
ixbrl_reporter/format.py
ixbrl_reporter/html.py
ixbrl_reporter/ixbrl_reporter.py
ixbrl_reporter/layout.py
ixbrl_reporter/note_heading.py
ixbrl_reporter/note_parse.py
ixbrl_reporter/notes.py
ixbrl_reporter/page.py
ixbrl_reporter/period.py
ixbrl_reporter/result.py
ixbrl_reporter/simple_sheet.py
ixbrl_reporter/table.py
ixbrl_reporter/taxonomy.py
ixbrl_reporter/text_reporter.py
ixbrl_reporter/valueset.py
ixbrl_reporter/worksheet.py
ixbrl_reporter/worksheet_element.py
ixbrl_reporter.egg-info/PKG-INFO
ixbrl_reporter.egg-info/SOURCES.txt
ixbrl_reporter.egg-info/dependency_links.txt
ixbrl_reporter.egg-info/entry_points.txt
ixbrl_reporter.egg-info/requires.txt
ixbrl_reporter.egg-info/top_level.txt