Metadata-Version: 2.4
Name: ixbrl-reporter
Version: 1.2.0
Summary: Production of iXBRL reports from templates and accounts files
Author-email: Cybermaggedon <mark@cyberapocalypse.co.uk>
License: GPL-3.0-or-later
Project-URL: Homepage, https://github.com/cybermaggedon/ixbrl-reporter
Project-URL: Download, https://github.com/cybermaggedon/ixbrl-reporter/archive/refs/tags/v1.1.0.tar.gz
Classifier: Programming Language :: Python :: 3
Classifier: License :: OSI Approved :: GNU General Public License v3 or later (GPLv3+)
Classifier: Operating System :: OS Independent
Requires-Python: >=3.6
License-File: LICENSE
Requires-Dist: requests
Requires-Dist: lxml
Requires-Dist: piecash
Requires-Dist: PyYAML
Provides-Extra: test
Requires-Dist: pytest>=7.0; extra == "test"
Requires-Dist: pytest-cov>=4.0; extra == "test"
Requires-Dist: pytest-mock>=3.10; extra == "test"
Requires-Dist: pyyaml>=6.0; extra == "test"
Dynamic: license-file
